[
  {
    "description": "Boavista inference",
    "agent_index": 0,
    "features": {
      "timestamp": "2026-02-22T08:00:00Z",
      "sites": {
        "boavista": {
          "non_shiftable_load": 5.0,
          "solar_generation": 1.5,
          "energy_price": 0.10,
          "charging_sessions": {
            "AC000004_1": {"power": 2.0, "electric_vehicle": "11824"}
          },
          "electric_vehicles": {
            "11824": {
              "SoC": 0.30,
              "flexibility": {
                "estimated_soc_at_departure": 0.90,
                "estimated_time_at_departure": "2026-02-22T09:30:00Z"
              }
            }
          }
        }
      }
    }
  },
  {
    "description": "Sao Mamede inference with virtual battery",
    "agent_index": 1,
    "features": {
      "timestamp": "2026-02-22T08:15:00Z",
      "sites": {
        "sao_mamede": {
          "site": {"pt_available_kw": 90.0},
          "solar_generation": 12.0,
          "charging_sessions": {
            "BB000SMI": {"power": 0.0, "electric_vehicle": "SM_EV_01"}
          },
          "electric_vehicles": {
            "SM_EV_01": {
              "SoC": 0.35,
              "flexibility": {
                "estimated_soc_at_departure": 0.80,
                "estimated_time_at_departure": "2026-02-22T12:00:00Z"
              }
            }
          },
          "electrical_storage": {"soc": 0.50},
          "virtual_battery": {"setpoint_kw": 30.0}
        }
      }
    }
  },
  {
    "description": "RH1 inference",
    "agent_index": 2,
    "features": {
      "timestamp": "2026-02-22T08:30:00Z",
      "sites": {
        "rh1": {
          "non_shiftable_load": 2.0,
          "solar_generation": 0.8,
          "electricity_pricing": {
            "current": 0.19,
            "h1": 0.18,
            "h2": 0.20,
            "h6": 0.22,
            "h12": 0.24,
            "h24": 0.21
          },
          "grid": {
            "import_limit_kw": 8.0,
            "export_limit_kw": 8.0
          },
          "electrical_storage": {"soc": 0.60},
          "cooling": {
            "temperature": {
              "current_c": 25.0,
              "min_c": 22.0,
              "max_c": 26.0
            }
          },
          "dhw": {
            "temperature": {
              "current_c": 44.0,
              "min_c": 42.0,
              "max_c": 52.0
            }
          },
          "charging_sessions": {
            "EVC01": {
              "power": 0.0,
              "electric_vehicle": "EV1"
            }
          },
          "electric_vehicles": {
            "EV1": {
              "SoC": 0.25,
              "flexibility": {
                "estimated_soc_at_departure": 0.75,
                "estimated_time_at_departure": "2026-02-22T11:30:00Z"
              }
            }
          }
        }
      }
    }
  }
]
